[
    {
        "代码":"000809",
        "名称":"和展能源",
        "Potential_Score":3.3723611243,
        "l2name":"房地产开发II",
        "Price20-day-MA_IsUp":true,
        "Price10-day-MA_IsUp":false,
        "PB":1.24,
        "PE":null,
        "ROE":-1.64,
        "DY":null,
        "PG":null,
        "RG":1025.11,
        "YC":9.89,
        "Price":4.0,
        "TR":15.53,
        "DA":17.62,
        "Percent":-8.47,
        "North":null,
        "TShare":8.25,
        "FShare":8.25,
        "Amount":5.5,
        "沪深300":0,
        "上证50":0,
        "中证A50":0,
        "中证500":0,
        "中证1000":0,
        "中证2000":0,
        "科创50":0,
        "300医药":0,
        "中证医疗":0,
        "电子50":0,
        "疫苗生物":0,
        "沪深300权重":0.0,
        "上证50权重":0.0,
        "中证A50权重":0.0,
        "中证500权重":0.0,
        "中证1000权重":0.0,
        "中证2000权重":0.0,
        "科创50权重":0.0,
        "医药权重":0.0,
        "中证医疗权重":0.0,
        "电子50权重":0.0,
        "疫苗生物权重":0.0,
        "Price5-day-MA":4.024,
        "Amount5-day-MA":1.662,
        "DA5-day-MA":5.74,
        "Price20-day-MA":3.8515,
        "Amount20-day-MA":1.052,
        "DA20-day-MA":4.057,
        "Price10-day-MA":3.978,
        "Amount10-day-MA":1.263,
        "DA10-day-MA":4.668,
        "TR5-day-MA":4.808,
        "TR10-day-MA":3.73,
        "TR20-day-MA":3.217,
        "endterdays":null,
        "Price5-day-Slope":0.0054972514,
        "Amount5-day-Slope":1.3541076487,
        "DA5-day-Slope":0.9644079398,
        "Price20-day-Slope":0.005482313,
        "Amount20-day-Slope":0.3141786384,
        "DA20-day-Slope":0.2175870348
    },
    {
        "代码":"603316",
        "名称":"诚邦股份",
        "Potential_Score":2.0995842072,
        "l2name":"基础建设II",
        "Price20-day-MA_IsUp":true,
        "Price10-day-MA_IsUp":true,
        "PB":13.03,
        "PE":null,
        "ROE":-16.45,
        "DY":null,
        "PG":106.32,
        "RG":31.07,
        "YC":87.93,
        "Price":27.25,
        "TR":30.8,
        "DA":13.77,
        "Percent":10.01,
        "North":null,
        "TShare":2.64,
        "FShare":2.64,
        "Amount":21.31,
        "沪深300":0,
        "上证50":0,
        "中证A50":0,
        "中证500":0,
        "中证1000":0,
        "中证2000":0,
        "科创50":0,
        "300医药":0,
        "中证医疗":0,
        "电子50":0,
        "疫苗生物":0,
        "沪深300权重":0.0,
        "上证50权重":0.0,
        "中证A50权重":0.0,
        "中证500权重":0.0,
        "中证1000权重":0.0,
        "中证2000权重":0.0,
        "科创50权重":0.0,
        "医药权重":0.0,
        "中证医疗权重":0.0,
        "电子50权重":0.0,
        "疫苗生物权重":0.0,
        "Price5-day-MA":22.724,
        "Amount5-day-MA":8.302,
        "DA5-day-MA":9.088,
        "Price20-day-MA":18.453,
        "Amount20-day-MA":5.209,
        "DA20-day-MA":6.4815,
        "Price10-day-MA":20.794,
        "Amount10-day-MA":6.968,
        "DA10-day-MA":6.729,
        "TR5-day-MA":13.438,
        "TR10-day-MA":12.352,
        "TR20-day-MA":10.0715,
        "endterdays":null,
        "Price5-day-Slope":0.0836433,
        "Amount5-day-Slope":0.8055676381,
        "DA5-day-Slope":0.3302107728,
        "Price20-day-Slope":0.0317873019,
        "Amount20-day-Slope":0.2324618479,
        "DA20-day-Slope":0.0905190544
    },
    {
        "代码":"301322",
        "名称":"绿通科技",
        "Potential_Score":2.0410533477,
        "l2name":"其他交运设备II",
        "Price20-day-MA_IsUp":true,
        "Price10-day-MA_IsUp":true,
        "PB":2.85,
        "PE":622.74,
        "ROE":0.46,
        "DY":0.09,
        "PG":null,
        "RG":6.97,
        "YC":105.9,
        "Price":56.58,
        "TR":25.65,
        "DA":13.75,
        "Percent":4.55,
        "North":null,
        "TShare":1.43,
        "FShare":0.96,
        "Amount":14.12,
        "沪深300":0,
        "上证50":0,
        "中证A50":0,
        "中证500":0,
        "中证1000":0,
        "中证2000":1,
        "科创50":0,
        "300医药":0,
        "中证医疗":0,
        "电子50":0,
        "疫苗生物":0,
        "沪深300权重":0.0,
        "上证50权重":0.0,
        "中证A50权重":0.0,
        "中证500权重":0.0,
        "中证1000权重":0.0,
        "中证2000权重":0.022,
        "科创50权重":0.0,
        "医药权重":0.0,
        "中证医疗权重":0.0,
        "电子50权重":0.0,
        "疫苗生物权重":0.0,
        "Price5-day-MA":48.422,
        "Amount5-day-MA":4.328,
        "DA5-day-MA":6.716,
        "Price20-day-MA":41.0515,
        "Amount20-day-MA":2.0405,
        "DA20-day-MA":5.5285,
        "Price10-day-MA":44.774,
        "Amount10-day-MA":2.79,
        "DA10-day-MA":5.83,
        "TR5-day-MA":8.562,
        "TR10-day-MA":5.855,
        "TR20-day-MA":4.73,
        "endterdays":null,
        "Price5-day-Slope":0.0622120827,
        "Amount5-day-Slope":1.2802950474,
        "DA5-day-Slope":0.2341051084,
        "Price20-day-Slope":0.0253902835,
        "Amount20-day-Slope":0.4512802276,
        "DA20-day-Slope":0.1131581597
    },
    {
        "代码":"300721",
        "名称":"怡达股份",
        "Potential_Score":1.9621533231,
        "l2name":"化学制品II",
        "Price20-day-MA_IsUp":true,
        "Price10-day-MA_IsUp":true,
        "PB":4.65,
        "PE":null,
        "ROE":-5.99,
        "DY":null,
        "PG":null,
        "RG":13.2,
        "YC":146.98,
        "Price":31.44,
        "TR":23.28,
        "DA":12.23,
        "Percent":-4.15,
        "North":null,
        "TShare":1.65,
        "FShare":1.38,
        "Amount":10.82,
        "沪深300":0,
        "上证50":0,
        "中证A50":0,
        "中证500":0,
        "中证1000":0,
        "中证2000":1,
        "科创50":0,
        "300医药":0,
        "中证医疗":0,
        "电子50":0,
        "疫苗生物":0,
        "沪深300权重":0.0,
        "上证50权重":0.0,
        "中证A50权重":0.0,
        "中证500权重":0.0,
        "中证1000权重":0.0,
        "中证2000权重":0.029,
        "科创50权重":0.0,
        "医药权重":0.0,
        "中证医疗权重":0.0,
        "电子50权重":0.0,
        "疫苗生物权重":0.0,
        "Price5-day-MA":31.796,
        "Amount5-day-MA":12.85,
        "DA5-day-MA":10.638,
        "Price20-day-MA":23.1525,
        "Amount20-day-MA":7.4115,
        "DA20-day-MA":9.488,
        "Price10-day-MA":26.765,
        "Amount10-day-MA":9.139,
        "DA10-day-MA":9.702,
        "TR5-day-MA":28.636,
        "TR10-day-MA":23.404,
        "TR20-day-MA":21.8335,
        "endterdays":null,
        "Price5-day-Slope":0.0458522466,
        "Amount5-day-Slope":0.0167748061,
        "DA5-day-Slope":-0.0859254167,
        "Price20-day-Slope":0.0385547033,
        "Amount20-day-Slope":0.0758455509,
        "DA20-day-Slope":0.0596381505
    },
    {
        "代码":"002421",
        "名称":"达实智能",
        "Potential_Score":1.9445055943,
        "l2name":"IT服务II",
        "Price20-day-MA_IsUp":true,
        "Price10-day-MA_IsUp":true,
        "PB":3.09,
        "PE":null,
        "ROE":-20.69,
        "DY":null,
        "PG":null,
        "RG":-14.59,
        "YC":38.95,
        "Price":3.96,
        "TR":46.21,
        "DA":20.14,
        "Percent":-7.26,
        "North":0.1499,
        "TShare":21.21,
        "FShare":20.03,
        "Amount":39.32,
        "沪深300":0,
        "上证50":0,
        "中证A50":0,
        "中证500":0,
        "中证1000":1,
        "中证2000":0,
        "科创50":0,
        "300医药":0,
        "中证医疗":0,
        "电子50":0,
        "疫苗生物":0,
        "沪深300权重":0.0,
        "上证50权重":0.0,
        "中证A50权重":0.0,
        "中证500权重":0.0,
        "中证1000权重":0.1,
        "中证2000权重":0.0,
        "科创50权重":0.0,
        "医药权重":0.0,
        "中证医疗权重":0.0,
        "电子50权重":0.0,
        "疫苗生物权重":0.0,
        "Price5-day-MA":3.77,
        "Amount5-day-MA":16.522,
        "DA5-day-MA":9.758,
        "Price20-day-MA":3.1135,
        "Amount20-day-MA":5.6565,
        "DA20-day-MA":4.9455,
        "Price10-day-MA":3.38,
        "Amount10-day-MA":9.268,
        "DA10-day-MA":6.374,
        "TR5-day-MA":20.792,
        "TR10-day-MA":12.072,
        "TR20-day-MA":7.817,
        "endterdays":null,
        "Price5-day-Slope":0.0583941606,
        "Amount5-day-Slope":0.834962239,
        "DA5-day-Slope":0.4811778992,
        "Price20-day-Slope":0.0173174318,
        "Amount20-day-Slope":0.4620056862,
        "DA20-day-Slope":0.1824267782
    },
    {
        "代码":"001259",
        "名称":"利仁科技",
        "Potential_Score":1.7969066631,
        "l2name":"小家电II",
        "Price20-day-MA_IsUp":true,
        "Price10-day-MA_IsUp":true,
        "PB":8.91,
        "PE":520.15,
        "ROE":1.72,
        "DY":0.14,
        "PG":3.05,
        "RG":10.88,
        "YC":193.24,
        "Price":88.0,
        "TR":9.45,
        "DA":10.02,
        "Percent":9.28,
        "North":null,
        "TShare":0.74,
        "FShare":0.48,
        "Amount":3.9,
        "沪深300":0,
        "上证50":0,
        "中证A50":0,
        "中证500":0,
        "中证1000":0,
        "中证2000":0,
        "科创50":0,
        "300医药":0,
        "中证医疗":0,
        "电子50":0,
        "疫苗生物":0,
        "沪深300权重":0.0,
        "上证50权重":0.0,
        "中证A50权重":0.0,
        "中证500权重":0.0,
        "中证1000权重":0.0,
        "中证2000权重":0.0,
        "科创50权重":0.0,
        "医药权重":0.0,
        "中证医疗权重":0.0,
        "电子50权重":0.0,
        "疫苗生物权重":0.0,
        "Price5-day-MA":73.758,
        "Amount5-day-MA":3.712,
        "DA5-day-MA":7.148,
        "Price20-day-MA":46.5875,
        "Amount20-day-MA":1.3785,
        "DA20-day-MA":4.6075,
        "Price10-day-MA":59.812,
        "Amount10-day-MA":2.1,
        "DA10-day-MA":5.006,
        "TR5-day-MA":10.392,
        "TR10-day-MA":6.417,
        "TR20-day-MA":5.2345,
        "endterdays":null,
        "Price5-day-Slope":0.098275708,
        "Amount5-day-Slope":0.2464741437,
        "DA5-day-Slope":0.3895800933,
        "Price20-day-Slope":0.0642003792,
        "Amount20-day-Slope":0.1521103218,
        "DA20-day-Slope":0.063351027
    },
    {
        "代码":"000417",
        "名称":"合百集团",
        "Potential_Score":1.6895642121,
        "l2name":"一般零售II",
        "Price20-day-MA_IsUp":true,
        "Price10-day-MA_IsUp":true,
        "PB":1.52,
        "PE":48.65,
        "ROE":3.13,
        "DY":0.7,
        "PG":-19.67,
        "RG":-5.93,
        "YC":14.94,
        "Price":9.31,
        "TR":30.28,
        "DA":13.22,
        "Percent":-2.31,
        "North":null,
        "TShare":7.8,
        "FShare":7.79,
        "Amount":23.57,
        "沪深300":0,
        "上证50":0,
        "中证A50":0,
        "中证500":0,
        "中证1000":0,
        "中证2000":1,
        "科创50":0,
        "300医药":0,
        "中证医疗":0,
        "电子50":0,
        "疫苗生物":0,
        "沪深300权重":0.0,
        "上证50权重":0.0,
        "中证A50权重":0.0,
        "中证500权重":0.0,
        "中证1000权重":0.0,
        "中证2000权重":0.058,
        "科创50权重":0.0,
        "医药权重":0.0,
        "中证医疗权重":0.0,
        "电子50权重":0.0,
        "疫苗生物权重":0.0,
        "Price5-day-MA":8.504,
        "Amount5-day-MA":7.836,
        "DA5-day-MA":4.464,
        "Price20-day-MA":7.2005,
        "Amount20-day-MA":3.175,
        "DA20-day-MA":3.8675,
        "Price10-day-MA":7.841,
        "Amount10-day-MA":5.309,
        "DA10-day-MA":4.24,
        "TR5-day-MA":10.68,
        "TR10-day-MA":7.801,
        "TR20-day-MA":4.908,
        "endterdays":null,
        "Price5-day-Slope":0.0454880747,
        "Amount5-day-Slope":0.9453823237,
        "DA5-day-Slope":0.4693877551,
        "Price20-day-Slope":0.0202621325,
        "Amount20-day-Slope":0.5427599611,
        "DA20-day-Slope":0.1348298122
    },
    {
        "代码":"301013",
        "名称":"利和兴",
        "Potential_Score":1.5640167118,
        "l2name":"专用设备II",
        "Price20-day-MA_IsUp":true,
        "Price10-day-MA_IsUp":true,
        "PB":12.47,
        "PE":null,
        "ROE":-21.2,
        "DY":null,
        "PG":null,
        "RG":29.48,
        "YC":27.45,
        "Price":35.7,
        "TR":41.15,
        "DA":9.08,
        "Percent":-1.82,
        "North":null,
        "TShare":2.34,
        "FShare":1.89,
        "Amount":27.83,
        "沪深300":0,
        "上证50":0,
        "中证A50":0,
        "中证500":0,
        "中证1000":0,
        "中证2000":1,
        "科创50":0,
        "300医药":0,
        "中证医疗":0,
        "电子50":0,
        "疫苗生物":0,
        "沪深300权重":0.0,
        "上证50权重":0.0,
        "中证A50权重":0.0,
        "中证500权重":0.0,
        "中证1000权重":0.0,
        "中证2000权重":0.046,
        "科创50权重":0.0,
        "医药权重":0.0,
        "中证医疗权重":0.0,
        "电子50权重":0.0,
        "疫苗生物权重":0.0,
        "Price5-day-MA":31.844,
        "Amount5-day-MA":13.794,
        "DA5-day-MA":8.504,
        "Price20-day-MA":27.7075,
        "Amount20-day-MA":6.499,
        "DA20-day-MA":5.2675,
        "Price10-day-MA":30.026,
        "Amount10-day-MA":9.629,
        "DA10-day-MA":6.314,
        "TR5-day-MA":21.852,
        "TR10-day-MA":16.047,
        "TR20-day-MA":11.4905,
        "endterdays":null,
        "Price5-day-Slope":0.0528334325,
        "Amount5-day-Slope":0.5211733569,
        "DA5-day-Slope":0.1384203481,
        "Price20-day-Slope":0.0194451599,
        "Amount20-day-Slope":0.2209280481,
        "DA20-day-Slope":0.0515021459
    },
    {
        "代码":"603082",
        "名称":"北自科技",
        "Potential_Score":1.4539300235,
        "l2name":null,
        "Price20-day-MA_IsUp":false,
        "Price10-day-MA_IsUp":false,
        "PB":4.16,
        "PE":46.56,
        "ROE":9.09,
        "DY":1.38,
        "PG":-20.64,
        "RG":2.96,
        "YC":15.99,
        "Price":42.8,
        "TR":48.22,
        "DA":9.14,
        "Percent":-7.08,
        "North":-0.4021,
        "TShare":1.62,
        "FShare":0.41,
        "Amount":8.43,
        "沪深300":0,
        "上证50":0,
        "中证A50":0,
        "中证500":0,
        "中证1000":0,
        "中证2000":0,
        "科创50":0,
        "300医药":0,
        "中证医疗":0,
        "电子50":0,
        "疫苗生物":0,
        "沪深300权重":0.0,
        "上证50权重":0.0,
        "中证A50权重":0.0,
        "中证500权重":0.0,
        "中证1000权重":0.0,
        "中证2000权重":0.0,
        "科创50权重":0.0,
        "医药权重":0.0,
        "中证医疗权重":0.0,
        "电子50权重":0.0,
        "疫苗生物权重":0.0,
        "Price5-day-MA":45.774,
        "Amount5-day-MA":7.376,
        "DA5-day-MA":7.52,
        "Price20-day-MA":38.195,
        "Amount20-day-MA":2.243,
        "DA20-day-MA":4.1055,
        "Price10-day-MA":40.87,
        "Amount10-day-MA":4.064,
        "DA10-day-MA":6.159,
        "TR5-day-MA":40.188,
        "TR10-day-MA":22.656,
        "TR20-day-MA":12.802,
        "endterdays":null,
        "Price5-day-Slope":0.019374666,
        "Amount5-day-Slope":0.2191735537,
        "DA5-day-Slope":-0.0264111859,
        "Price20-day-Slope":0.0075178053,
        "Amount20-day-Slope":0.2150595883,
        "DA20-day-Slope":0.0964080652
    },
    {
        "代码":"688549",
        "名称":"中巨芯-U",
        "Potential_Score":1.4315122116,
        "l2name":null,
        "Price20-day-MA_IsUp":true,
        "Price10-day-MA_IsUp":true,
        "PB":7.73,
        "PE":null,
        "ROE":-0.3,
        "DY":null,
        "PG":86.89,
        "RG":22.4,
        "YC":72.7,
        "Price":15.75,
        "TR":25.73,
        "DA":12.28,
        "Percent":-12.11,
        "North":0.0108,
        "TShare":14.77,
        "FShare":5.89,
        "Amount":25.35,
        "沪深300":0,
        "上证50":0,
        "中证A50":0,
        "中证500":0,
        "中证1000":0,
        "中证2000":0,
        "科创50":0,
        "300医药":0,
        "中证医疗":0,
        "电子50":0,
        "疫苗生物":0,
        "沪深300权重":0.0,
        "上证50权重":0.0,
        "中证A50权重":0.0,
        "中证500权重":0.0,
        "中证1000权重":0.0,
        "中证2000权重":0.0,
        "科创50权重":0.0,
        "医药权重":0.0,
        "中证医疗权重":0.0,
        "电子50权重":0.0,
        "疫苗生物权重":0.0,
        "Price5-day-MA":17.256,
        "Amount5-day-MA":26.226,
        "DA5-day-MA":11.194,
        "Price20-day-MA":13.0445,
        "Amount20-day-MA":12.4885,
        "DA20-day-MA":8.015,
        "Price10-day-MA":15.195,
        "Amount10-day-MA":17.9,
        "DA10-day-MA":9.247,
        "TR5-day-MA":25.81,
        "TR10-day-MA":19.087,
        "TR20-day-MA":14.84,
        "endterdays":null,
        "Price5-day-Slope":0.0208234737,
        "Amount5-day-Slope":0.0969549941,
        "DA5-day-Slope":0.0376344086,
        "Price20-day-Slope":0.0249469631,
        "Amount20-day-Slope":0.1050303057,
        "DA20-day-Slope":0.0644797131
    },
    {
        "代码":"300657",
        "名称":"弘信电子",
        "Potential_Score":1.3975773843,
        "l2name":"元件II",
        "Price20-day-MA_IsUp":true,
        "Price10-day-MA_IsUp":true,
        "PB":16.62,
        "PE":132.41,
        "ROE":13.79,
        "DY":null,
        "PG":null,
        "RG":28.89,
        "YC":77.08,
        "Price":48.98,
        "TR":27.47,
        "DA":10.5,
        "Percent":-5.08,
        "North":-0.3206,
        "TShare":4.82,
        "FShare":4.69,
        "Amount":65.99,
        "沪深300":0,
        "上证50":0,
        "中证A50":0,
        "中证500":0,
        "中证1000":0,
        "中证2000":0,
        "科创50":0,
        "300医药":0,
        "中证医疗":0,
        "电子50":0,
        "疫苗生物":0,
        "沪深300权重":0.0,
        "上证50权重":0.0,
        "中证A50权重":0.0,
        "中证500权重":0.0,
        "中证1000权重":0.0,
        "中证2000权重":0.0,
        "科创50权重":0.0,
        "医药权重":0.0,
        "中证医疗权重":0.0,
        "电子50权重":0.0,
        "疫苗生物权重":0.0,
        "Price5-day-MA":46.446,
        "Amount5-day-MA":48.336,
        "DA5-day-MA":7.856,
        "Price20-day-MA":39.451,
        "Amount20-day-MA":25.1835,
        "DA20-day-MA":6.154,
        "Price10-day-MA":42.529,
        "Amount10-day-MA":34.138,
        "DA10-day-MA":6.738,
        "TR5-day-MA":20.504,
        "TR10-day-MA":15.725,
        "TR20-day-MA":12.625,
        "endterdays":null,
        "Price5-day-Slope":0.0507669336,
        "Amount5-day-Slope":0.2548286604,
        "DA5-day-Slope":0.0975132719,
        "Price20-day-Slope":0.0182348462,
        "Amount20-day-Slope":0.1213349066,
        "DA20-day-Slope":0.0647058824
    },
    {
        "代码":"002208",
        "名称":"合肥城建",
        "Potential_Score":1.3693942784,
        "l2name":"房地产开发II",
        "Price20-day-MA_IsUp":true,
        "Price10-day-MA_IsUp":true,
        "PB":3.16,
        "PE":null,
        "ROE":-8.95,
        "DY":null,
        "PG":85.58,
        "RG":20.31,
        "YC":88.13,
        "Price":23.29,
        "TR":16.87,
        "DA":10.09,
        "Percent":-10.01,
        "North":-0.167,
        "TShare":8.03,
        "FShare":8.03,
        "Amount":32.74,
        "沪深300":0,
        "上证50":0,
        "中证A50":0,
        "中证500":0,
        "中证1000":0,
        "中证2000":1,
        "科创50":0,
        "300医药":0,
        "中证医疗":0,
        "电子50":0,
        "疫苗生物":0,
        "沪深300权重":0.0,
        "上证50权重":0.0,
        "中证A50权重":0.0,
        "中证500权重":0.0,
        "中证1000权重":0.0,
        "中证2000权重":0.047,
        "科创50权重":0.0,
        "医药权重":0.0,
        "中证医疗权重":0.0,
        "电子50权重":0.0,
        "疫苗生物权重":0.0,
        "Price5-day-MA":23.578,
        "Amount5-day-MA":31.648,
        "DA5-day-MA":8.976,
        "Price20-day-MA":16.622,
        "Amount20-day-MA":13.4595,
        "DA20-day-MA":6.544,
        "Price10-day-MA":20.105,
        "Amount10-day-MA":22.419,
        "DA10-day-MA":8.201,
        "TR5-day-MA":16.728,
        "TR10-day-MA":13.248,
        "TR20-day-MA":8.7235,
        "endterdays":null,
        "Price5-day-Slope":0.030506993,
        "Amount5-day-Slope":0.0959966754,
        "DA5-day-Slope":0.112267658,
        "Price20-day-Slope":0.0339315149,
        "Amount20-day-Slope":0.1201314913,
        "DA20-day-Slope":0.0627689809
    },
    {
        "代码":"002407",
        "名称":"多氟多",
        "Potential_Score":1.2916375845,
        "l2name":"化学制品II",
        "Price20-day-MA_IsUp":true,
        "Price10-day-MA_IsUp":false,
        "PB":5.54,
        "PE":92.79,
        "ROE":6.06,
        "DY":0.47,
        "PG":34.17,
        "RG":6.6,
        "YC":20.98,
        "Price":40.81,
        "TR":26.85,
        "DA":7.89,
        "Percent":0.29,
        "North":-0.5103,
        "TShare":11.9,
        "FShare":10.79,
        "Amount":121.89,
        "沪深300":0,
        "上证50":0,
        "中证A50":0,
        "中证500":1,
        "中证1000":0,
        "中证2000":0,
        "科创50":0,
        "300医药":0,
        "中证医疗":0,
        "电子50":0,
        "疫苗生物":0,
        "沪深300权重":0.0,
        "上证50权重":0.0,
        "中证A50权重":0.0,
        "中证500权重":0.203,
        "中证1000权重":0.0,
        "中证2000权重":0.0,
        "科创50权重":0.0,
        "医药权重":0.0,
        "中证医疗权重":0.0,
        "电子50权重":0.0,
        "疫苗生物权重":0.0,
        "Price5-day-MA":38.588,
        "Amount5-day-MA":86.648,
        "DA5-day-MA":7.11,
        "Price20-day-MA":35.409,
        "Amount20-day-MA":61.269,
        "DA20-day-MA":6.369,
        "Price10-day-MA":36.512,
        "Amount10-day-MA":64.849,
        "DA10-day-MA":6.29,
        "TR5-day-MA":20.69,
        "TR10-day-MA":16.033,
        "TR20-day-MA":15.874,
        "endterdays":null,
        "Price5-day-Slope":0.0413428325,
        "Amount5-day-Slope":0.2585771141,
        "DA5-day-Slope":0.0868236013,
        "Price20-day-Slope":0.0153263846,
        "Amount20-day-Slope":0.090807125,
        "DA20-day-Slope":0.0461563732
    },
    {
        "代码":"003018",
        "名称":"金富科技",
        "Potential_Score":1.2417120071,
        "l2name":"包装印刷II",
        "Price20-day-MA_IsUp":true,
        "Price10-day-MA_IsUp":false,
        "PB":10.7,
        "PE":180.84,
        "ROE":5.95,
        "DY":0.3,
        "PG":-9.84,
        "RG":3.75,
        "YC":283.12,
        "Price":66.74,
        "TR":6.36,
        "DA":7.12,
        "Percent":-4.44,
        "North":null,
        "TShare":2.6,
        "FShare":2.37,
        "Amount":10.22,
        "沪深300":0,
        "上证50":0,
        "中证A50":0,
        "中证500":0,
        "中证1000":0,
        "中证2000":0,
        "科创50":0,
        "300医药":0,
        "中证医疗":0,
        "电子50":0,
        "疫苗生物":0,
        "沪深300权重":0.0,
        "上证50权重":0.0,
        "中证A50权重":0.0,
        "中证500权重":0.0,
        "中证1000权重":0.0,
        "中证2000权重":0.0,
        "科创50权重":0.0,
        "医药权重":0.0,
        "中证医疗权重":0.0,
        "电子50权重":0.0,
        "疫苗生物权重":0.0,
        "Price5-day-MA":65.454,
        "Amount5-day-MA":12.476,
        "DA5-day-MA":10.086,
        "Price20-day-MA":55.3,
        "Amount20-day-MA":9.002,
        "DA20-day-MA":7.104,
        "Price10-day-MA":57.533,
        "Amount10-day-MA":9.35,
        "DA10-day-MA":7.025,
        "TR5-day-MA":7.992,
        "TR10-day-MA":6.678,
        "TR20-day-MA":6.779,
        "endterdays":null,
        "Price5-day-Slope":0.0412994368,
        "Amount5-day-Slope":0.1488029466,
        "DA5-day-Slope":0.1643962133,
        "Price20-day-Slope":0.0218033999,
        "Amount20-day-Slope":0.0158551035,
        "DA20-day-Slope":-0.0184455959
    },
    {
        "代码":"603938",
        "名称":"三孚股份",
        "Potential_Score":1.2337902124,
        "l2name":"化学原料II",
        "Price20-day-MA_IsUp":true,
        "Price10-day-MA_IsUp":true,
        "PB":7.62,
        "PE":210.02,
        "ROE":3.69,
        "DY":0.04,
        "PG":-16.07,
        "RG":8.84,
        "YC":164.68,
        "Price":50.58,
        "TR":13.17,
        "DA":12.61,
        "Percent":-5.92,
        "North":0.1843,
        "TShare":3.83,
        "FShare":3.83,
        "Amount":26.93,
        "沪深300":0,
        "上证50":0,
        "中证A50":0,
        "中证500":0,
        "中证1000":1,
        "中证2000":0,
        "科创50":0,
        "300医药":0,
        "中证医疗":0,
        "电子50":0,
        "疫苗生物":0,
        "沪深300权重":0.0,
        "上证50权重":0.0,
        "中证A50权重":0.0,
        "中证500权重":0.0,
        "中证1000权重":0.037,
        "中证2000权重":0.0,
        "科创50权重":0.0,
        "医药权重":0.0,
        "中证医疗权重":0.0,
        "电子50权重":0.0,
        "疫苗生物权重":0.0,
        "Price5-day-MA":47.606,
        "Amount5-day-MA":14.04,
        "DA5-day-MA":9.934,
        "Price20-day-MA":36.5,
        "Amount20-day-MA":9.5675,
        "DA20-day-MA":7.249,
        "Price10-day-MA":43.087,
        "Amount10-day-MA":13.445,
        "DA10-day-MA":9.49,
        "TR5-day-MA":7.654,
        "TR10-day-MA":8.256,
        "TR20-day-MA":6.6155,
        "endterdays":null,
        "Price5-day-Slope":0.0342385401,
        "Amount5-day-Slope":0.1589895988,
        "DA5-day-Slope":0.0942938973,
        "Price20-day-Slope":0.0309715141,
        "Amount20-day-Slope":0.1121766928,
        "DA20-day-Slope":0.0415229885
    },
    {
        "代码":"300276",
        "名称":"三丰智能",
        "Potential_Score":1.2334022193,
        "l2name":"自动化设备II",
        "Price20-day-MA_IsUp":true,
        "Price10-day-MA_IsUp":false,
        "PB":7.37,
        "PE":null,
        "ROE":-11.04,
        "DY":null,
        "PG":168.72,
        "RG":-8.3,
        "YC":-5.05,
        "Price":9.21,
        "TR":18.58,
        "DA":11.0,
        "Percent":6.6,
        "North":-0.0601,
        "TShare":14.01,
        "FShare":10.57,
        "Amount":17.7,
        "沪深300":0,
        "上证50":0,
        "中证A50":0,
        "中证500":0,
        "中证1000":0,
        "中证2000":1,
        "科创50":0,
        "300医药":0,
        "中证医疗":0,
        "电子50":0,
        "疫苗生物":0,
        "沪深300权重":0.0,
        "上证50权重":0.0,
        "中证A50权重":0.0,
        "中证500权重":0.0,
        "中证1000权重":0.0,
        "中证2000权重":0.069,
        "科创50权重":0.0,
        "医药权重":0.0,
        "中证医疗权重":0.0,
        "电子50权重":0.0,
        "疫苗生物权重":0.0,
        "Price5-day-MA":8.844,
        "Amount5-day-MA":14.336,
        "DA5-day-MA":9.678,
        "Price20-day-MA":7.593,
        "Amount20-day-MA":5.258,
        "DA20-day-MA":5.1275,
        "Price10-day-MA":8.052,
        "Amount10-day-MA":8.359,
        "DA10-day-MA":6.638,
        "TR5-day-MA":15.448,
        "TR10-day-MA":9.266,
        "TR20-day-MA":6.047,
        "endterdays":null,
        "Price5-day-Slope":0.0521056388,
        "Amount5-day-Slope":0.2811438785,
        "DA5-day-Slope":0.1730909091,
        "Price20-day-Slope":0.0133457894,
        "Amount20-day-Slope":0.179055948,
        "DA20-day-Slope":0.1018588159
    },
    {
        "代码":"002272",
        "名称":"川润股份",
        "Potential_Score":1.0501276364,
        "l2name":"通用机械II",
        "Price20-day-MA_IsUp":false,
        "Price10-day-MA_IsUp":false,
        "PB":7.46,
        "PE":null,
        "ROE":-1.89,
        "DY":null,
        "PG":-24.39,
        "RG":3.46,
        "YC":37.31,
        "Price":22.45,
        "TR":38.4,
        "DA":9.62,
        "Percent":-9.98,
        "North":null,
        "TShare":4.85,
        "FShare":4.08,
        "Amount":37.3,
        "沪深300":0,
        "上证50":0,
        "中证A50":0,
        "中证500":0,
        "中证1000":0,
        "中证2000":1,
        "科创50":0,
        "300医药":0,
        "中证医疗":0,
        "电子50":0,
        "疫苗生物":0,
        "沪深300权重":0.0,
        "上证50权重":0.0,
        "中证A50权重":0.0,
        "中证500权重":0.0,
        "中证1000权重":0.0,
        "中证2000权重":0.041,
        "科创50权重":0.0,
        "医药权重":0.0,
        "中证医疗权重":0.0,
        "电子50权重":0.0,
        "疫苗生物权重":0.0,
        "Price5-day-MA":21.882,
        "Amount5-day-MA":17.12,
        "DA5-day-MA":7.298,
        "Price20-day-MA":19.7045,
        "Amount20-day-MA":12.6765,
        "DA20-day-MA":5.951,
        "Price10-day-MA":20.749,
        "Amount10-day-MA":13.739,
        "DA10-day-MA":5.842,
        "TR5-day-MA":18.49,
        "TR10-day-MA":15.684,
        "TR20-day-MA":15.3935,
        "endterdays":null,
        "Price5-day-Slope":0.0308083663,
        "Amount5-day-Slope":0.4700326292,
        "DA5-day-Slope":0.1255397903,
        "Price20-day-Slope":0.0046140512,
        "Amount20-day-Slope":0.0642683234,
        "DA20-day-Slope":0.0436688881
    },
    {
        "代码":"002150",
        "名称":"正泰电源",
        "Potential_Score":0.8922098219,
        "l2name":"通用机械II",
        "Price20-day-MA_IsUp":false,
        "Price10-day-MA_IsUp":false,
        "PB":5.67,
        "PE":44.11,
        "ROE":13.61,
        "DY":0.29,
        "PG":53.13,
        "RG":17.86,
        "YC":69.1,
        "Price":33.99,
        "TR":11.34,
        "DA":6.17,
        "Percent":-1.11,
        "North":-0.3367,
        "TShare":3.61,
        "FShare":3.59,
        "Amount":13.84,
        "沪深300":0,
        "上证50":0,
        "中证A50":0,
        "中证500":0,
        "中证1000":0,
        "中证2000":1,
        "科创50":0,
        "300医药":0,
        "中证医疗":0,
        "电子50":0,
        "疫苗生物":0,
        "沪深300权重":0.0,
        "上证50权重":0.0,
        "中证A50权重":0.0,
        "中证500权重":0.0,
        "中证1000权重":0.0,
        "中证2000权重":0.072,
        "科创50权重":0.0,
        "医药权重":0.0,
        "中证医疗权重":0.0,
        "电子50权重":0.0,
        "疫苗生物权重":0.0,
        "Price5-day-MA":32.102,
        "Amount5-day-MA":11.29,
        "DA5-day-MA":9.262,
        "Price20-day-MA":29.7905,
        "Amount20-day-MA":6.562,
        "DA20-day-MA":5.221,
        "Price10-day-MA":30.554,
        "Amount10-day-MA":7.891,
        "DA10-day-MA":6.484,
        "TR5-day-MA":9.74,
        "TR10-day-MA":7.014,
        "TR20-day-MA":6.0205,
        "endterdays":null,
        "Price5-day-Slope":0.0360831397,
        "Amount5-day-Slope":0.19648156,
        "DA5-day-Slope":0.0095923261,
        "Price20-day-Slope":0.0068269767,
        "Amount20-day-Slope":0.0658653456,
        "DA20-day-Slope":0.0369414101
    },
    {
        "代码":"000880",
        "名称":"潍柴重机",
        "Potential_Score":0.7563394829,
        "l2name":"汽车零部件II",
        "Price20-day-MA_IsUp":true,
        "Price10-day-MA_IsUp":false,
        "PB":7.35,
        "PE":60.17,
        "ROE":12.41,
        "DY":0.53,
        "PG":36.53,
        "RG":44.88,
        "YC":25.22,
        "Price":34.21,
        "TR":27.49,
        "DA":9.15,
        "Percent":-3.42,
        "North":-0.2574,
        "TShare":4.64,
        "FShare":2.27,
        "Amount":21.97,
        "沪深300":0,
        "上证50":0,
        "中证A50":0,
        "中证500":0,
        "中证1000":0,
        "中证2000":1,
        "科创50":0,
        "300医药":0,
        "中证医疗":0,
        "电子50":0,
        "疫苗生物":0,
        "沪深300权重":0.0,
        "上证50权重":0.0,
        "中证A50权重":0.0,
        "中证500权重":0.0,
        "中证1000权重":0.0,
        "中证2000权重":0.032,
        "科创50权重":0.0,
        "医药权重":0.0,
        "中证医疗权重":0.0,
        "电子50权重":0.0,
        "疫苗生物权重":0.0,
        "Price5-day-MA":33.132,
        "Amount5-day-MA":12.886,
        "DA5-day-MA":5.734,
        "Price20-day-MA":31.2775,
        "Amount20-day-MA":9.919,
        "DA20-day-MA":4.464,
        "Price10-day-MA":31.895,
        "Amount10-day-MA":11.212,
        "DA10-day-MA":5.178,
        "TR5-day-MA":17.004,
        "TR10-day-MA":15.22,
        "TR20-day-MA":13.7425,
        "endterdays":null,
        "Price5-day-Slope":0.0108616061,
        "Amount5-day-Slope":0.0183341236,
        "DA5-day-Slope":0.1504815409,
        "Price20-day-Slope":0.0049318854,
        "Amount20-day-Slope":0.0466392318,
        "DA20-day-Slope":-0.0182537937
    },
    {
        "代码":"001258",
        "名称":"立新能源",
        "Potential_Score":0.576470405,
        "l2name":"电力II",
        "Price20-day-MA_IsUp":true,
        "Price10-day-MA_IsUp":false,
        "PB":3.16,
        "PE":95.66,
        "ROE":3.39,
        "DY":0.29,
        "PG":null,
        "RG":9.38,
        "YC":45.29,
        "Price":10.33,
        "TR":9.98,
        "DA":10.79,
        "Percent":7.16,
        "North":0.4357,
        "TShare":9.33,
        "FShare":9.33,
        "Amount":9.65,
        "沪深300":0,
        "上证50":0,
        "中证A50":0,
        "中证500":0,
        "中证1000":1,
        "中证2000":0,
        "科创50":0,
        "300医药":0,
        "中证医疗":0,
        "电子50":0,
        "疫苗生物":0,
        "沪深300权重":0.0,
        "上证50权重":0.0,
        "中证A50权重":0.0,
        "中证500权重":0.0,
        "中证1000权重":0.033,
        "中证2000权重":0.0,
        "科创50权重":0.0,
        "医药权重":0.0,
        "中证医疗权重":0.0,
        "电子50权重":0.0,
        "疫苗生物权重":0.0,
        "Price5-day-MA":10.018,
        "Amount5-day-MA":6.242,
        "DA5-day-MA":8.274,
        "Price20-day-MA":9.542,
        "Amount20-day-MA":4.6425,
        "DA20-day-MA":5.413,
        "Price10-day-MA":9.822,
        "Amount10-day-MA":5.436,
        "DA10-day-MA":6.678,
        "TR5-day-MA":6.556,
        "TR10-day-MA":5.828,
        "TR20-day-MA":5.143,
        "endterdays":null,
        "Price5-day-Slope":0.0166429876,
        "Amount5-day-Slope":0.179070646,
        "DA5-day-Slope":0.1082239486,
        "Price20-day-Slope":0.0068587106,
        "Amount20-day-Slope":0.0799023029,
        "DA20-day-Slope":0.0742210756
    }
]