{
    "update_time_bjt": "2025-10-29 15:26:57",
    "trade_date": "2025-10-29",
    "top_up_20": [
        {
            "代码": "159371",
            "名称": "创业板50ETF富国",
            "Price": 1.8,
            "Percent": 12.29,
            "Amount": 0.12
        },
        {
            "代码": "516290",
            "名称": "光伏龙头ETF",
            "Price": 0.63,
            "Percent": 8.81,
            "Amount": 1.32
        },
        {
            "代码": "159857",
            "名称": "光伏ETF",
            "Price": 0.858,
            "Percent": 8.75,
            "Amount": 5.35
        },
        {
            "代码": "159864",
            "名称": "光伏50ETF",
            "Price": 0.656,
            "Percent": 8.25,
            "Amount": 0.7
        },
        {
            "代码": "515790",
            "名称": "光伏ETF",
            "Price": 1.01,
            "Percent": 8.25,
            "Amount": 18.03
        },
        {
            "代码": "516880",
            "名称": "光伏50ETF",
            "Price": 0.853,
            "Percent": 8.25,
            "Amount": 1.26
        },
        {
            "代码": "516180",
            "名称": "光伏ETF基金",
            "Price": 0.831,
            "Percent": 8.2,
            "Amount": 0.22
        },
        {
            "代码": "159609",
            "名称": "光伏龙头ETF",
            "Price": 0.584,
            "Percent": 8.15,
            "Amount": 0.65
        },
        {
            "代码": "159618",
            "名称": "光伏ETF指数基金",
            "Price": 0.8,
            "Percent": 8.11,
            "Amount": 0.16
        },
        {
            "代码": "562970",
            "名称": "光伏ETF易方达",
            "Price": 1.148,
            "Percent": 8.1,
            "Amount": 0.37
        },
        {
            "代码": "159863",
            "名称": "光伏ETF基金",
            "Price": 0.666,
            "Percent": 7.94,
            "Amount": 0.34
        },
        {
            "代码": "560980",
            "名称": "光伏ETF龙头",
            "Price": 0.724,
            "Percent": 7.9,
            "Amount": 1.07
        },
        {
            "代码": "159796",
            "名称": "电池50ETF",
            "Price": 1.025,
            "Percent": 6.55,
            "Amount": 10.54
        },
        {
            "代码": "516090",
            "名称": "新能源ETF易方达",
            "Price": 0.573,
            "Percent": 6.51,
            "Amount": 1.03
        },
        {
            "代码": "562880",
            "名称": "电池ETF嘉实",
            "Price": 0.889,
            "Percent": 6.47,
            "Amount": 1.66
        },
        {
            "代码": "159875",
            "名称": "新能源ETF",
            "Price": 0.695,
            "Percent": 6.43,
            "Amount": 1.86
        },
        {
            "代码": "561910",
            "名称": "电池ETF",
            "Price": 0.871,
            "Percent": 6.35,
            "Amount": 8.51
        },
        {
            "代码": "561160",
            "名称": "锂电池ETF",
            "Price": 0.872,
            "Percent": 6.34,
            "Amount": 2.91
        },
        {
            "代码": "159387",
            "名称": "创业板新能源ETF国泰",
            "Price": 1.735,
            "Percent": 6.25,
            "Amount": 0.22
        },
        {
            "代码": "516160",
            "名称": "新能源ETF",
            "Price": 2.94,
            "Percent": 6.25,
            "Amount": 4.62
        }
    ],
    "top_down_20": [
        {
            "代码": "516310",
            "名称": "银行ETF易方达",
            "Price": 1.341,
            "Percent": -1.97,
            "Amount": 0.76
        },
        {
            "代码": "515290",
            "名称": "银行ETF天弘",
            "Price": 1.456,
            "Percent": -1.95,
            "Amount": 0.97
        },
        {
            "代码": "512730",
            "名称": "银行ETF指数",
            "Price": 1.663,
            "Percent": -1.95,
            "Amount": 0.18
        },
        {
            "代码": "159887",
            "名称": "银行ETF",
            "Price": 1.321,
            "Percent": -1.93,
            "Amount": 3.15
        },
        {
            "代码": "512800",
            "名称": "银行ETF",
            "Price": 0.813,
            "Percent": -1.93,
            "Amount": 21.58
        },
        {
            "代码": "516210",
            "名称": "银行ETF指数基金",
            "Price": 1.382,
            "Percent": -1.92,
            "Amount": 0.16
        },
        {
            "代码": "515020",
            "名称": "银行ETF基金",
            "Price": 1.723,
            "Percent": -1.88,
            "Amount": 0.5
        },
        {
            "代码": "512820",
            "名称": "银行ETF龙头",
            "Price": 1.426,
            "Percent": -1.86,
            "Amount": 1.74
        },
        {
            "代码": "512700",
            "名称": "银行ETF南方",
            "Price": 1.643,
            "Percent": -1.85,
            "Amount": 1.49
        },
        {
            "代码": "517900",
            "名称": "银行AH优选ETF",
            "Price": 1.486,
            "Percent": -1.65,
            "Amount": 0.44
        },
        {
            "代码": "159518",
            "名称": "标普油气ETF",
            "Price": 0.885,
            "Percent": -1.01,
            "Amount": 2.85
        },
        {
            "代码": "512890",
            "名称": "红利低波ETF",
            "Price": 1.187,
            "Percent": -0.92,
            "Amount": 6.89
        },
        {
            "代码": "513350",
            "名称": "标普油气ETF",
            "Price": 0.934,
            "Percent": -0.85,
            "Amount": 1.02
        },
        {
            "代码": "159525",
            "名称": "红利低波ETF",
            "Price": 1.109,
            "Percent": -0.81,
            "Amount": 0.17
        },
        {
            "代码": "560890",
            "名称": "红利低波ETF新华",
            "Price": 1.227,
            "Percent": -0.81,
            "Amount": 0.0
        },
        {
            "代码": "159547",
            "名称": "红利低波ETF基金",
            "Price": 1.22,
            "Percent": -0.81,
            "Amount": 0.2
        },
        {
            "代码": "589120",
            "名称": "科创创新药ETF汇添富",
            "Price": 0.869,
            "Percent": -0.8,
            "Amount": 0.27
        },
        {
            "代码": "588130",
            "名称": "科创医药ETF基金",
            "Price": 1.162,
            "Percent": -0.77,
            "Amount": 0.09
        },
        {
            "代码": "563690",
            "名称": "红利低波ETF永赢",
            "Price": 1.042,
            "Percent": -0.76,
            "Amount": 0.06
        },
        {
            "代码": "589720",
            "名称": "科创创新药ETF国泰",
            "Price": 0.934,
            "Percent": -0.74,
            "Amount": 1.01
        }
    ]
}