{
    "update_time_bjt": "2025-07-18 10:54:03",
    "trade_date": "2025-07-18",
    "top_up_20": [
        {
            "代码": "00080",
            "名称": "中国新经济投资",
            "Price": 0.455,
            "Percent": 411.24,
            "Amount": 0.49
        },
        {
            "代码": "01862",
            "名称": "景瑞控股",
            "Price": 0.018,
            "Percent": 38.46,
            "Amount": 0.02
        },
        {
            "代码": "00969",
            "名称": "华联国际",
            "Price": 0.15,
            "Percent": 37.61,
            "Amount": 0.01
        },
        {
            "代码": "01119",
            "名称": "创梦天地",
            "Price": 1.08,
            "Percent": 30.12,
            "Amount": 0.35
        },
        {
            "代码": "00334",
            "名称": "华显光电",
            "Price": 0.33,
            "Percent": 22.22,
            "Amount": 0.02
        },
        {
            "代码": "01536",
            "名称": "煜荣集团",
            "Price": 0.113,
            "Percent": 21.51,
            "Amount": 0.0
        },
        {
            "代码": "00399",
            "名称": "领航医药生物科技",
            "Price": 0.445,
            "Percent": 20.27,
            "Amount": 0.18
        },
        {
            "代码": "01341",
            "名称": "昊天国际建投",
            "Price": 0.231,
            "Percent": 19.07,
            "Amount": 12.48
        },
        {
            "代码": "00197",
            "名称": "亨泰",
            "Price": 0.28,
            "Percent": 17.65,
            "Amount": 0.0
        },
        {
            "代码": "00106",
            "名称": "朗诗绿色管理",
            "Price": 0.021,
            "Percent": 16.67,
            "Amount": 0.0
        },
        {
            "代码": "06833",
            "名称": "兴科蓉医药",
            "Price": 0.27,
            "Percent": 16.38,
            "Amount": 0.0
        },
        {
            "代码": "00138",
            "名称": "中建富通",
            "Price": 0.079,
            "Percent": 16.18,
            "Amount": 0.0
        },
        {
            "代码": "00645",
            "名称": "安域亚洲",
            "Price": 0.113,
            "Percent": 15.31,
            "Amount": 0.0
        },
        {
            "代码": "01340",
            "名称": "惠生国际",
            "Price": 0.041,
            "Percent": 13.89,
            "Amount": 0.0
        },
        {
            "代码": "01472",
            "名称": "生兴控股",
            "Price": 0.067,
            "Percent": 13.56,
            "Amount": 0.0
        },
        {
            "代码": "01797",
            "名称": "东方甄选",
            "Price": 16.3,
            "Percent": 13.19,
            "Amount": 4.05
        },
        {
            "代码": "06928",
            "名称": "万马控股",
            "Price": 0.52,
            "Percent": 13.04,
            "Amount": 0.05
        },
        {
            "代码": "02263",
            "名称": "富石金融",
            "Price": 0.325,
            "Percent": 12.07,
            "Amount": 0.0
        },
        {
            "代码": "02517",
            "名称": "锅圈",
            "Price": 3.8,
            "Percent": 11.44,
            "Amount": 4.4
        },
        {
            "代码": "01672",
            "名称": "歌礼制药-B",
            "Price": 10.88,
            "Percent": 10.46,
            "Amount": 0.44
        }
    ],
    "top_down_20": [
        {
            "代码": "00630",
            "名称": "隽泰控股",
            "Price": 0.33,
            "Percent": -16.46,
            "Amount": 0.01
        },
        {
            "代码": "01166",
            "名称": "星凯控股",
            "Price": 0.49,
            "Percent": -14.04,
            "Amount": 0.0
        },
        {
            "代码": "00333",
            "名称": "黛丽斯国际",
            "Price": 0.265,
            "Percent": -11.67,
            "Amount": 0.0
        },
        {
            "代码": "01141",
            "名称": "民银资本",
            "Price": 0.68,
            "Percent": -10.53,
            "Amount": 0.01
        },
        {
            "代码": "02425",
            "名称": "澳亚集团",
            "Price": 1.39,
            "Percent": -9.74,
            "Amount": 0.0
        },
        {
            "代码": "01888",
            "名称": "建滔积层板",
            "Price": 9.8,
            "Percent": -9.59,
            "Amount": 11.66
        },
        {
            "代码": "01676",
            "名称": "高地股份",
            "Price": 0.58,
            "Percent": -9.38,
            "Amount": 0.0
        },
        {
            "代码": "00318",
            "名称": "黄河实业",
            "Price": 0.4,
            "Percent": -9.09,
            "Amount": 0.0
        },
        {
            "代码": "01217",
            "名称": "中国创新投资",
            "Price": 0.01,
            "Percent": -9.09,
            "Amount": 0.0
        },
        {
            "代码": "02017",
            "名称": "沧海控股",
            "Price": 0.255,
            "Percent": -8.93,
            "Amount": 0.0
        },
        {
            "代码": "00707",
            "名称": "亚洲电视控股",
            "Price": 0.062,
            "Percent": -8.82,
            "Amount": 0.0
        },
        {
            "代码": "01620",
            "名称": "富盈环球集团",
            "Price": 0.056,
            "Percent": -8.2,
            "Amount": 0.0
        },
        {
            "代码": "00559",
            "名称": "德泰新能源集团",
            "Price": 0.217,
            "Percent": -8.05,
            "Amount": 0.01
        },
        {
            "代码": "00913",
            "名称": "港湾数字",
            "Price": 0.355,
            "Percent": -7.79,
            "Amount": 0.0
        },
        {
            "代码": "02276",
            "名称": "康耐特光学",
            "Price": 43.3,
            "Percent": -7.48,
            "Amount": 0.88
        },
        {
            "代码": "01719",
            "名称": "中国通商集团",
            "Price": 0.62,
            "Percent": -7.46,
            "Amount": 0.0
        },
        {
            "代码": "01753",
            "名称": "兑吧",
            "Price": 0.25,
            "Percent": -7.41,
            "Amount": 0.01
        },
        {
            "代码": "02660",
            "名称": "禅游科技",
            "Price": 2.54,
            "Percent": -7.3,
            "Amount": 0.06
        },
        {
            "代码": "01967",
            "名称": "信恳智能",
            "Price": 0.45,
            "Percent": -7.22,
            "Amount": 0.0
        },
        {
            "代码": "01722",
            "名称": "建鹏控股",
            "Price": 0.065,
            "Percent": -7.14,
            "Amount": 0.0
        }
    ]
}