{
    "update_time_bjt": "2026-03-11 14:15:44",
    "trade_date": "2026-03-11",
    "top_up_20": [
        {
            "代码": "00913",
            "名称": "港湾数字",
            "Price": 0.38,
            "Percent": 58.33,
            "Amount": 0.02
        },
        {
            "代码": "00875",
            "名称": "从玉智农",
            "Price": 0.83,
            "Percent": 27.69,
            "Amount": 0.04
        },
        {
            "代码": "06651",
            "名称": "五一视界",
            "Price": 60.0,
            "Percent": 27.12,
            "Amount": 2.54
        },
        {
            "代码": "02656",
            "名称": "健康160",
            "Price": 109.1,
            "Percent": 23.84,
            "Amount": 1.55
        },
        {
            "代码": "01303",
            "名称": "汇力资源",
            "Price": 0.24,
            "Percent": 20.6,
            "Amount": 0.0
        },
        {
            "代码": "01823",
            "名称": "华昱高速",
            "Price": 1.64,
            "Percent": 18.84,
            "Amount": 0.02
        },
        {
            "代码": "01094",
            "名称": "承辉国际",
            "Price": 0.54,
            "Percent": 18.68,
            "Amount": 0.03
        },
        {
            "代码": "02627",
            "名称": "中慧生物-B",
            "Price": 71.0,
            "Percent": 18.33,
            "Amount": 1.65
        },
        {
            "代码": "01837",
            "名称": "五谷磨房",
            "Price": 1.32,
            "Percent": 16.81,
            "Amount": 0.19
        },
        {
            "代码": "02665",
            "名称": "图达通",
            "Price": 11.88,
            "Percent": 16.7,
            "Amount": 2.85
        },
        {
            "代码": "00313",
            "名称": "裕田中国",
            "Price": 0.086,
            "Percent": 16.22,
            "Amount": 0.0
        },
        {
            "代码": "01643",
            "名称": "现代中药集团",
            "Price": 1.45,
            "Percent": 15.08,
            "Amount": 0.02
        },
        {
            "代码": "09866",
            "名称": "蔚来-SW",
            "Price": 43.82,
            "Percent": 14.89,
            "Amount": 5.46
        },
        {
            "代码": "00794",
            "名称": "锦胜集团(控股)",
            "Price": 0.24,
            "Percent": 14.83,
            "Amount": 0.0
        },
        {
            "代码": "02427",
            "名称": "GUANZE MEDICAL",
            "Price": 3.99,
            "Percent": 14.0,
            "Amount": 0.11
        },
        {
            "代码": "02181",
            "名称": "迈博药业-B",
            "Price": 0.49,
            "Percent": 13.95,
            "Amount": 0.04
        },
        {
            "代码": "00641",
            "名称": "中国恒天立信国际",
            "Price": 0.305,
            "Percent": 12.96,
            "Amount": 0.0
        },
        {
            "代码": "02892",
            "名称": "万城控股",
            "Price": 0.405,
            "Percent": 12.5,
            "Amount": 0.0
        },
        {
            "代码": "01959",
            "名称": "中聚投资",
            "Price": 4.88,
            "Percent": 12.18,
            "Amount": 0.07
        },
        {
            "代码": "01198",
            "名称": "皇朝家居",
            "Price": 0.113,
            "Percent": 11.88,
            "Amount": 0.0
        }
    ],
    "top_down_20": [
        {
            "代码": "03336",
            "名称": "巨腾国际",
            "Price": 2.33,
            "Percent": -21.02,
            "Amount": 0.7
        },
        {
            "代码": "01707",
            "名称": "致浩达控股",
            "Price": 0.04,
            "Percent": -16.67,
            "Amount": 0.0
        },
        {
            "代码": "00464",
            "名称": "中国智能科技",
            "Price": 0.77,
            "Percent": -14.44,
            "Amount": 0.01
        },
        {
            "代码": "02025",
            "名称": "瑞丰动力",
            "Price": 17.25,
            "Percent": -13.75,
            "Amount": 0.09
        },
        {
            "代码": "01920",
            "名称": "中国网成",
            "Price": 0.73,
            "Percent": -13.1,
            "Amount": 0.06
        },
        {
            "代码": "02442",
            "名称": "怡俊集团控股",
            "Price": 10.19,
            "Percent": -13.05,
            "Amount": 0.01
        },
        {
            "代码": "00574",
            "名称": "百信国际",
            "Price": 0.048,
            "Percent": -12.73,
            "Amount": 0.0
        },
        {
            "代码": "01333",
            "名称": "博雷顿",
            "Price": 22.3,
            "Percent": -12.55,
            "Amount": 0.93
        },
        {
            "代码": "01407",
            "名称": "交运燃气",
            "Price": 0.49,
            "Percent": -12.5,
            "Amount": 0.01
        },
        {
            "代码": "02371",
            "名称": "创联控股",
            "Price": 0.255,
            "Percent": -12.07,
            "Amount": 0.0
        },
        {
            "代码": "01280",
            "名称": "奇点国峰",
            "Price": 1.74,
            "Percent": -11.68,
            "Amount": 0.02
        },
        {
            "代码": "00827",
            "名称": "玖源集团",
            "Price": 0.04,
            "Percent": -11.11,
            "Amount": 0.01
        },
        {
            "代码": "02685",
            "名称": "量化派",
            "Price": 34.2,
            "Percent": -10.66,
            "Amount": 1.29
        },
        {
            "代码": "01026",
            "名称": "环球实业科技",
            "Price": 0.094,
            "Percent": -10.48,
            "Amount": 0.0
        },
        {
            "代码": "02889",
            "名称": "博泰车联",
            "Price": 180.1,
            "Percent": -10.4,
            "Amount": 0.29
        },
        {
            "代码": "06696",
            "名称": "多想云",
            "Price": 3.02,
            "Percent": -10.12,
            "Amount": 0.08
        },
        {
            "代码": "02582",
            "名称": "国富氢能",
            "Price": 31.84,
            "Percent": -10.11,
            "Amount": 2.25
        },
        {
            "代码": "00474",
            "名称": "信铭生命科技",
            "Price": 0.108,
            "Percent": -10.0,
            "Amount": 0.0
        },
        {
            "代码": "00617",
            "名称": "百利保控股",
            "Price": 0.195,
            "Percent": -9.72,
            "Amount": 0.02
        },
        {
            "代码": "01173",
            "名称": "威高国际",
            "Price": 0.028,
            "Percent": -9.68,
            "Amount": 0.0
        }
    ]
}