[
    {
        "代码": "01833",
        "名称": "平安好医生",
        "Price": 15.45,
        "Percent": 7.22,
        "Amount": 6.15,
        "update_time_bjt": "2025-08-15 14:23:55",
        "trade_date": "2025-08-15"
    },
    {
        "代码": "01919",
        "名称": "中远海控",
        "Price": 14.47,
        "Percent": -1.03,
        "Amount": 1.93,
        "update_time_bjt": "2025-08-15 14:23:55",
        "trade_date": "2025-08-15"
    },
    {
        "代码": "00659",
        "名称": "周大福创建",
        "Price": 7.75,
        "Percent": -0.51,
        "Amount": 0.06,
        "update_time_bjt": "2025-08-15 14:23:55",
        "trade_date": "2025-08-15"
    },
    {
        "代码": "00316",
        "名称": "东方海外国际",
        "Price": 145.2,
        "Percent": -1.56,
        "Amount": 0.99,
        "update_time_bjt": "2025-08-15 14:23:55",
        "trade_date": "2025-08-15"
    },
    {
        "代码": "01308",
        "名称": "海丰国际",
        "Price": 27.22,
        "Percent": -0.15,
        "Amount": 0.86,
        "update_time_bjt": "2025-08-15 14:23:55",
        "trade_date": "2025-08-15"
    },
    {
        "代码": "01171",
        "名称": "兖矿能源",
        "Price": 9.33,
        "Percent": 0.32,
        "Amount": 2.17,
        "update_time_bjt": "2025-08-15 14:23:55",
        "trade_date": "2025-08-15"
    },
    {
        "代码": "00288",
        "名称": "万洲国际",
        "Price": 8.01,
        "Percent": -2.55,
        "Amount": 1.32,
        "update_time_bjt": "2025-08-15 14:23:55",
        "trade_date": "2025-08-15"
    },
    {
        "代码": "00564",
        "名称": "中创智领",
        "Price": 16.12,
        "Percent": -0.19,
        "Amount": 0.11,
        "update_time_bjt": "2025-08-15 14:23:55",
        "trade_date": "2025-08-15"
    },
    {
        "代码": "02285",
        "名称": "泉峰控股",
        "Price": 23.2,
        "Percent": 0.35,
        "Amount": 0.21,
        "update_time_bjt": "2025-08-15 14:23:55",
        "trade_date": "2025-08-15"
    },
    {
        "代码": "01378",
        "名称": "中国宏桥",
        "Price": 23.28,
        "Percent": 4.02,
        "Amount": 5.0,
        "update_time_bjt": "2025-08-15 14:23:55",
        "trade_date": "2025-08-15"
    },
    {
        "代码": "00598",
        "名称": "中国外运",
        "Price": 4.51,
        "Percent": -0.66,
        "Amount": 0.06,
        "update_time_bjt": "2025-08-15 14:23:55",
        "trade_date": "2025-08-15"
    },
    {
        "代码": "00327",
        "名称": "百富环球",
        "Price": 6.85,
        "Percent": -1.44,
        "Amount": 0.32,
        "update_time_bjt": "2025-08-15 14:23:55",
        "trade_date": "2025-08-15"
    },
    {
        "代码": "01548",
        "名称": "金斯瑞生物科技",
        "Price": 17.62,
        "Percent": 0.69,
        "Amount": 1.69,
        "update_time_bjt": "2025-08-15 14:23:55",
        "trade_date": "2025-08-15"
    },
    {
        "代码": "00857",
        "名称": "中国石油股份",
        "Price": 7.67,
        "Percent": -0.52,
        "Amount": 3.21,
        "update_time_bjt": "2025-08-15 14:23:55",
        "trade_date": "2025-08-15"
    },
    {
        "代码": "01088",
        "名称": "中国神华",
        "Price": 36.74,
        "Percent": -1.92,
        "Amount": 6.13,
        "update_time_bjt": "2025-08-15 14:23:55",
        "trade_date": "2025-08-15"
    },
    {
        "代码": "01336",
        "名称": "新华保险",
        "Price": 52.2,
        "Percent": 2.55,
        "Amount": 6.57,
        "update_time_bjt": "2025-08-15 14:23:55",
        "trade_date": "2025-08-15"
    },
    {
        "代码": "00363",
        "名称": "上海实业控股",
        "Price": 14.86,
        "Percent": -0.73,
        "Amount": 0.05,
        "update_time_bjt": "2025-08-15 14:23:55",
        "trade_date": "2025-08-15"
    },
    {
        "代码": "01800",
        "名称": "中国交通建设",
        "Price": 5.83,
        "Percent": 0.34,
        "Amount": 0.41,
        "update_time_bjt": "2025-08-15 14:23:55",
        "trade_date": "2025-08-15"
    },
    {
        "代码": "00101",
        "名称": "恒隆地产",
        "Price": 8.18,
        "Percent": -0.24,
        "Amount": 0.48,
        "update_time_bjt": "2025-08-15 14:23:55",
        "trade_date": "2025-08-15"
    },
    {
        "代码": "00384",
        "名称": "中国燃气",
        "Price": 8.4,
        "Percent": 1.08,
        "Amount": 0.42,
        "update_time_bjt": "2025-08-15 14:23:55",
        "trade_date": "2025-08-15"
    }
]